README
setup.py
AdvancedLangConv.egg-info/PKG-INFO
AdvancedLangConv.egg-info/SOURCES.txt
AdvancedLangConv.egg-info/dependency_links.txt
AdvancedLangConv.egg-info/top_level.txt
langconv/__init__.py
langconv/converter.c
langconv/globalfunc.py
langconv/langconv.py
langconv/messages.py
langconv/settings.py
langconv/defaulttables/__init__.py
langconv/defaulttables/zh_cn.py
langconv/defaulttables/zh_custom.py
langconv/defaulttables/zh_hans.py
langconv/defaulttables/zh_hant.py
langconv/defaulttables/zh_hk.py
langconv/defaulttables/zh_sg.py
langconv/defaulttables/zh_tw.py