Metadata-Version: 1.0
Name: AdvancedLangConv
Version: 0.01
Summary: Advanced Language Converter
Home-page: http://code.google.com/p/advanced-langconv/
Author: UNKNOWN
Author-email: UNKNOWN
License: UNKNOWN
Platform: UNKNOWN
